LICENSE.txt
MANIFEST.in
README.txt
setup.py
pcart_messaging/__init__.py
pcart_messaging/admin.py
pcart_messaging/apps.py
pcart_messaging/email_backend.py
pcart_messaging/html2text.py
pcart_messaging/models.py
pcart_messaging/tasks.py
pcart_messaging/utils.py
pcart_messaging.egg-info/PKG-INFO
pcart_messaging.egg-info/SOURCES.txt
pcart_messaging.egg-info/dependency_links.txt
pcart_messaging.egg-info/not-zip-safe
pcart_messaging.egg-info/requires.txt
pcart_messaging.egg-info/top_level.txt
pcart_messaging/locale/ru/LC_MESSAGES/django.mo
pcart_messaging/locale/ru/LC_MESSAGES/django.po
pcart_messaging/locale/uk/LC_MESSAGES/django.mo
pcart_messaging/locale/uk/LC_MESSAGES/django.po
pcart_messaging/migrations/0001_initial.py
pcart_messaging/migrations/__init__.py